{
	"name": "DSkvEMP",
	"properties": {
		"linkedServiceName": {
			"referenceName": "AzureSqlDBKV",
			"type": "LinkedServiceReference"
		},
		"annotations": [],
		"type": "AzureSqlTable",
		"schema": [
			{
				"name": "empno",
				"type": "int",
				"precision": 10
			},
			{
				"name": "ename",
				"type": "varchar"
			},
			{
				"name": "job",
				"type": "varchar"
			},
			{
				"name": "mgr",
				"type": "int",
				"precision": 10
			},
			{
				"name": "hiredate",
				"type": "varchar"
			},
			{
				"name": "sal",
				"type": "int",
				"precision": 10
			},
			{
				"name": "comm",
				"type": "int",
				"precision": 10
			},
			{
				"name": "deptno",
				"type": "int",
				"precision": 10
			}
		],
		"typeProperties": {
			"schema": "dbo",
			"table": "emp"
		}
	}
}